{"noMoreComments": true, "cursorEnd": 0, "id": "4686033", "comments": [{"postBy": {"location": "\u53f0\u4e2d\u5e02\u00b7\u53f0\u7063", "utc": 1476608300000, "level": 0, "avatar": "http://filestoresg1.beetalkmobile.com:8081/file/-952356288792942904", "name": "\u4efb\u6211\u884c"}, "content": "\u4e2d\u4f4e\u968e\u5c64\u9664\u4e86\u9152\u99d5<br />\u9084\u9700\u8981\u70e4\uff0c\u70b8\uff0c\u6ef7\u7684\u98df\u7269<br />\u4f86\u914d\u9152<br />", "urls": [], "replies": {"first": [{"content": "\u6069\u963f  \u592a\u5ee3\u4e86", "reply": "", "id": 33377440, "name": "\u963f\u97f6"}], "last": [], "noMoreReplies": true}, "images": [], "id": 50417235}, {"postBy": {"location": "\u6843\u5712\u5e02\u00b7\u53f0\u7063", "utc": 1476614644000, "level": 0, "avatar": "http://filestoresg1.beetalkmobile.com:8081/file/5888249811864429214", "name": "\u5f35 \u5c0f\u96e8"}, "content": "\u9999\u8178\u6524\u554a~\uff01<br /><br />\u5e73\u50f9\u7f8e\u98df\u3002\u591a\u7a2e\u642d\u914d\u3002\u5165\u9580\u7c21\u55ae\u3002\u5c0f\u672c\u7d93\u71df\u3002\u73a9\u6cd5\u591a\u6a23", "urls": [], "replies": {"first": [{"content": "\u54c8\u54c8  \u88ab\u4f60\u8aaa\u7684\u5f88\u751f\u52d5!!", "reply": "", "id": 33379790, "name": "\u963f\u97f6"}], "last": [{"content": "\u5225\u8aaa\u4e86\u3002\u3002\u3002\u7897\u516c\u62ff\u4f86\u3002\u3002\u3002\u5341\u516b\u8fa3\u3002", "reply": "\u53ef\u53ef", "id": 33384504, "name": "\u5f35 \u5c0f\u96e8"}, {"content": "\u679c\u7136\u53b2\u5bb3! \u6211\u8003\u616e\u770b\u770b", "reply": "\u5f35 \u5c0f\u96e8", "id": 33384569, "name": "\u963f\u97f6"}], "noMoreReplies": false}, "images": [], "id": 50420423}, {"postBy": {"location": "\u9ad8\u96c4\u5e02\u00b7\u53f0\u7063", "utc": 1476615242000, "level": 0, "avatar": "http://filestoresg1.beetalkmobile.com:8081/file/8089529277963221576", "name": "\u6bcf\u5929\u90fd\u8981\u9032\u6b65"}, "content": "\u8ce3\u51b0\u26c4", "urls": [], "replies": {"first": [{"content": "\u597d\u50cf\u4e5f\u53ef", "reply": "", "id": 33379808, "name": "\u963f\u97f6"}], "last": [], "noMoreReplies": true}, "images": [], "id": 50420738}, {"postBy": {"location": "\u65b0\u5317\u5e02\u00b7\u53f0\u7063", "utc": 1476615456000, "level": 0, "avatar": "http://filestoresg1.beetalkmobile.com:8081/file/-5796133815167238778", "name": "\u5c0f\u660c\u660c"}, "content": "\u5730\u9ede\uff0c\u5730\u9ede\uff0c\u9084\u662f\u5730\u9ede\uff0c\u5f88\u91cd\u8981\u6240\u4ee5\u8aaa\u4e09\u6b21\uff0c\u597d\u7684\u5730\u9ede\u96a8\u4fbf\u8ce3\u90fd\u53ef\u4ee5\u8cfa\u9322\uff0c\u4e0d\u904e\u5225\u4e09\u5fc3\u4e8c\u610f\u5594\u3002", "urls": [], "replies": {"first": [{"content": "\u4e0d\u932f", "reply": "", "id": 33379902, "name": "\u963f\u97f6"}], "last": [], "noMoreReplies": true}, "images": [], "id": 50420850}, {"postBy": {"location": "\u9ad8\u96c4\u5e02\u00b7\u53f0\u7063", "utc": 1476618461000, "level": 0, "avatar": "http://filestoresg1.beetalkmobile.com:8081/file/631334083342711866", "name": "\u5f97\u4e86\u4e00\u7a2e\u653e\u982d\u8cbc\u5c31\u6703\u6b7b\u6389\u7684\u75c5"}, "content": "\u96de\u86cb\u7cd5\u6216\u662f\u68c9\u82b1\u7cd6", "urls": [], "replies": {"first": [], "last": [], "noMoreReplies": true}, "images": [], "id": 50422495}, {"postBy": {"location": "\u53f0\u5317\u5e02\u00b7\u53f0\u7063", "utc": 1476620531000, "level": 0, "avatar": "http://filestoresg1.beetalkmobile.com:8081/file/5742102724118632723", "name": " \u738b \u5c3c\u746a "}, "content": "\u9e79\u6c34\u96de", "urls": [], "replies": {"first": [], "last": [], "noMoreReplies": true}, "images": [], "id": 50423764}, {"postBy": {"location": "\u53f0\u4e2d\u5e02\u00b7\u53f0\u7063", "utc": 1476631605000, "level": 0, "avatar": "http://filestoresg1.beetalkmobile.com:8081/file/-952356288792942904", "name": "\u4efb\u6211\u884c"}, "content": "\u5176\u5be6\u820a\u6709\u7684\u7d20\u6750<br />\u80fd\u5275\u65b0 <br />\u5927\u773e\u80fd\u63a5\u53d7<br />\u4f60\u5c31\u80fd\u6210\u529f\u4e00\u534a\u4e86", "urls": [], "replies": {"first": [], "last": [], "noMoreReplies": true}, "images": [], "id": 50430997}]}
