{"noMoreComments": true, "cursorEnd": 0, "id": "4452926", "comments": [{"postBy": {"location": "\u9ad8\u96c4\u5e02\u00b7\u53f0\u7063", "utc": 1473343473000, "level": 0, "avatar": "http://filestoresg1.beetalkmobile.com:8081/file/563015929551564720", "name": "Victor"}, "content": "\u8b9a\u5594!", "urls": [], "replies": {"first": [], "last": [], "noMoreReplies": true}, "images": [], "id": 47766260}, {"postBy": {"location": "\u65b0\u7af9\u7e23\u00b7\u53f0\u7063", "utc": 1473352564000, "level": 0, "avatar": "http://filestoresg1.beetalkmobile.com:8081/file/-1108460534813640075", "name": "\u8001\u5175"}, "content": "\u8001\u5c07\u80fd\u7e7c\u7e8c\u5728\u7403\u5834\u4e0a\uff0c\u7e3d\u662f\u6709\u5e7e\u628a\u5237\u5b50", "urls": [], "replies": {"first": [], "last": [], "noMoreReplies": true}, "images": [], "id": 47778431}]}
