{"noMoreComments": false, "cursorEnd": 26, "id": "4352079", "comments": [{"postBy": {"location": "\u65b0\u7af9\u5e02\u00b7\u53f0\u7063", "utc": 1471860800000, "level": 0, "avatar": "http://filestoresg1.beetalkmobile.com:8081/file/-9172022639064933064", "name": "\u80a5\u561f\u561f"}, "content": "\u55ef \u5f88\u4e0d\u932f\u554a", "urls": [], "replies": {"first": [{"content": "\u5c0d\u963f", "reply": "", "id": 30572802, "name": "Ny\ud83d\udc8b"}], "last": [], "noMoreReplies": true}, "images": [], "id": 46491581}, {"postBy": {"location": "\u65b0\u5317\u5e02\u00b7\u53f0\u7063", "utc": 1471861220000, "level": 0, "avatar": "http://filestoresg1.beetalkmobile.com:8081/file/-7730320990265772190", "name": "\ud83d\ude0d\ud83d\ude0d\ud83d\ude0d\ud83d\ude0d\ud83d\ude0d\ud83d\ude0d"}, "content": "\ud83d\ude08\ud83d\ude08\ud83d\ude08\ud83d\ude08", "urls": [], "replies": {"first": [{"content": "\ud83d\ude11", "reply": "", "id": 30572820, "name": "Ny\ud83d\udc8b"}, {"content": "\ud83d\udc4d\ud83d\udc4d\ud83d\udc4d", "reply": "Ny\ud83d\udc8b", "id": 30573296, "name": "\ud83d\ude0d\ud83d\ude0d\ud83d\ude0d\ud83d\ude0d\ud83d\ude0d\ud83d\ude0d"}], "last": [], "noMoreReplies": true}, "images": [], "id": 46491956}, {"postBy": {"location": "\u65b0\u5317\u5e02\u00b7\u53f0\u7063", "utc": 1471861549000, "level": 0, "avatar": "http://filestoresg1.beetalkmobile.com:8081/file/6228065987217044135", "name": "Chleh mln"}, "content": "\u53ef\u4ee5\u770b\u770b\u6211\u7684\u7c21\u4ecb", "urls": [], "replies": {"first": [{"content": "\u600e\u9ebc\u4e86", "reply": "", "id": 30572836, "name": "Ny\ud83d\udc8b"}], "last": [], "noMoreReplies": true}, "images": [], "id": 46492221}, {"postBy": {"location": "\u65b0\u5317\u5e02\u00b7\u53f0\u7063", "utc": 1471861942000, "level": 0, "avatar": "http://filestoresg1.beetalkmobile.com:8081/file/1993649890088707895", "name": "\u9b6f\u5c0f\u5c0f"}, "content": "\u59b3\u9858\u610f\u7b49\u4e00\u500b\u6574\u5929\u6c92\u4e8b\u505a\u7684\u4eba\u55ce", "urls": [], "replies": {"first": [{"content": "\u6211\u770b\u611f\u89ba", "reply": "", "id": 30572848, "name": "Ny\ud83d\udc8b"}], "last": [], "noMoreReplies": true}, "images": [], "id": 46492548}, {"postBy": {"location": "\u53f0\u5357\u5e02\u00b7\u53f0\u7063", "utc": 1471862037000, "level": 0, "avatar": "http://filestoresg1.beetalkmobile.com:8081/file/-2394923238705317193", "name": "\u5f35\u667a\u8d85"}, "content": "\u6211\u53ef\u4ee5\u8a66\u8a66\u55ce", "urls": [], "replies": {"first": [{"content": "\u7576\u7136", "reply": "", "id": 30572855, "name": "Ny\ud83d\udc8b"}, {"content": "\u771f\u7684\u9084\u5047\u7684", "reply": "Ny\ud83d\udc8b", "id": 30582923, "name": "\u5f35\u667a\u8d85"}], "last": [], "noMoreReplies": true}, "images": [], "id": 46492623}, {"postBy": {"location": "\u9ad8\u96c4\u5e02\u00b7\u53f0\u7063", "utc": 1471862054000, "level": 0, "avatar": "http://filestoresg1.beetalkmobile.com:8081/file/-875643362887468542", "name": "\u5c0f\u5b5f"}, "content": "\u9019\u662f\u7406\u60f3\u7537\u53cb", "urls": [], "replies": {"first": [{"content": "\u7576\u7136", "reply": "", "id": 30572869, "name": "Ny\ud83d\udc8b"}, {"content": "\u9019\u4e9b\u4e4b\u524d\u505a\u904e\uff0c\u4f46\u5f80\u5f80\u5634\u4e0a\u639b\u8457\u8aaa\u7d50\u5a5a\u5e7e\u4e4e\u5f88\u5c11\u6703\u9054\u6210", "reply": "Ny\ud83d\udc8b", "id": 30637618, "name": "\u5c0f\u5b5f"}], "last": [], "noMoreReplies": true}, "images": [], "id": 46492635}, {"postBy": {"location": "", "utc": 1471862310000, "level": 0, "avatar": "http://filestoresg1.beetalkmobile.com:8081/file/45924408807064478", "name": "\u88dd\u4e0d\u6eff\u7684\u9152\u676f"}, "content": "\u53ef\u60dc\u62b1\u4e0d\u5230", "urls": [], "replies": {"first": [{"content": "\u54c8\u54c8\u60f3\u62b1\uff1f", "reply": "", "id": 30572884, "name": "Ny\ud83d\udc8b"}], "last": [{"content": "\u54c8\u54c8", "reply": "Ny\ud83d\udc8b", "id": 30572943, "name": "\u88dd\u4e0d\u6eff\u7684\u9152\u676f"}, {"content": "\u6de1\u6de1\u54c0\u50b7", "reply": "Ny\ud83d\udc8b", "id": 30572966, "name": "\u88dd\u4e0d\u6eff\u7684\u9152\u676f"}], "noMoreReplies": true}, "images": [], "id": 46492817}, {"postBy": {"location": "\u6843\u5712\u5e02\u00b7\u53f0\u7063", "utc": 1471862818000, "level": 0, "avatar": "http://filestoresg1.beetalkmobile.com:8081/file/-83758594667829479", "name": "\u963f\u5049"}, "content": "\u5973\u4eba\u671f\u671b\u4f55\u5617\u4e0d\u662f\u7537\u4eba\u671f\u671b\ud83d\ude02\ud83d\ude02\ud83d\ude02\ud83d\ude02", "urls": [], "replies": {"first": [{"content": "\u54c8\u54c8\u4e0d\u77e5\u9053\u56c9", "reply": "", "id": 30572898, "name": "Ny\ud83d\udc8b"}, {"content": "\u771f\u7684\u55ce\uff1f\ud83d\ude02\ud83d\ude02\ud83d\ude02\ud83d\ude02", "reply": "", "id": 30579775, "name": "\u963f\u5049"}], "last": [], "noMoreReplies": true}, "images": [], "id": 46493276}, {"postBy": {"location": "\u5609\u7fa9\u7e23\u00b7\u53f0\u7063", "utc": 1471863062000, "level": 0, "avatar": "http://filestoresg1.beetalkmobile.com:8081/file/-3209454649254688510", "name": "Kelvin\ud83c\udf1e\ud83d\udeb6"}, "content": "\u6211\u53ef\u4ee5\u8ddf\u4f60\u7576\u500b\u670b\u53cb\u804a\u804a\u5929\uff1f", "urls": [], "replies": {"first": [{"content": "\u53e3\u4ee5\u5440", "reply": "", "id": 30572908, "name": "Ny\ud83d\udc8b"}, {"content": "\u52a0\u4f60\u4e86\u5594", "reply": "Ny\ud83d\udc8b", "id": 30574179, "name": "Kelvin\ud83c\udf1e\ud83d\udeb6"}], "last": [], "noMoreReplies": true}, "images": [], "id": 46493485}, {"postBy": {"location": "\u65b0\u5317\u5e02\u00b7\u53f0\u7063", "utc": 1471863080000, "level": 0, "avatar": "http://filestoresg1.beetalkmobile.com:8081/file/4650935537218816", "name": "\u4e16\u5049"}, "content": "\u7406\u60f3\u7537\u4eba\uff01\u4f86\u8a8d\u8b58\u958b\u69d3++", "urls": [], "replies": {"first": [{"content": "\u54c8\u54c8\u6c34", "reply": "", "id": 30572915, "name": "Ny\ud83d\udc8b"}, {"content": "\u7d66\u6a5f\u6703\u804a\u5929\u4ea4\u6d41\u4e00\u4e0b\u54e6", "reply": "Ny\ud83d\udc8b", "id": 30572969, "name": "\u4e16\u5049"}], "last": [], "noMoreReplies": true}, "images": [], "id": 46493501}, {"postBy": {"location": "\u65b0\u7af9\u5e02\u00b7\u53f0\u7063", "utc": 1471870797000, "level": 0, "avatar": "http://filestoresg1.beetalkmobile.com:8081/file/-4325672252576466660", "name": "\u4f86\u81eaNG\u4e16\u754c\u7684\u4e00\u676f\u7d05\u8336"}, "content": "\u6709\u6642\u5225\u7b49\uff0c\u8aaa\u4e0d\u5b9a\u5df2\u7d93\u6709\u4e86\uff0c\u7d50\u679c\u4f60\u4e00\u53e5\u6211\u9084\u5728\u7b49\uff0c\u90a3\u500b\u6a5f\u6703\u6703\u98db\u8d70", "urls": [], "replies": {"first": [{"content": "\u54c8\u54c8", "reply": "", "id": 30572942, "name": "Ny\ud83d\udc8b"}], "last": [], "noMoreReplies": true}, "images": [], "id": 46502004}, {"postBy": {"location": "\u65b0\u5317\u5e02\u00b7\u53f0\u7063", "utc": 1471870880000, "level": 0, "avatar": "http://filestoresg1.beetalkmobile.com:8081/file/4108635261305544734", "name": "Smrt lin"}, "content": "\u6709\u9019\u6a23\u7684\u4e8b\uff01", "urls": [], "replies": {"first": [{"content": "\ud83d\ude22\ud83d\ude22\ud83d\ude22\u5716\u7247\u611f\u4eba", "reply": "", "id": 30572980, "name": "Ny\ud83d\udc8b"}], "last": [], "noMoreReplies": true}, "images": ["http://filestoresg1.beetalkmobile.com:8081/file/9c26aa432dfc917b6a853f53d2b9db6b"], "id": 46502115}, {"postBy": {"location": "\u53f0\u5317\u5e02\u00b7\u53f0\u7063", "utc": 1471872266000, "level": 0, "avatar": "http://filestoresg1.beetalkmobile.com:8081/file/-8625454308710629696", "name": "K\u7d00"}, "content": "\u6bcf\u5929 \u90fd\u8aaa\u5ac1\u7d66\u6211\u7684\u611f\u89ba \u633a\u6577\u884d\u7684\u5427 \u9084\u662f\u4e45\u4e45\u4e00\u6b21 \u6216\u8005 \u53ea\u9700\u4e00\u6b21 \u6bd4\u8f03\u6709\u611f\u89f8<br /><br />\u5e0c\u671b \u4f60\u80fd\u9047\u5230 \u52a0\u6cb9\u5427", "urls": [], "replies": {"first": [{"content": "\u4e00\u7a2e\u60c5\u8da3\u800c\u5df2", "reply": "", "id": 30620299, "name": "Ny\ud83d\udc8b"}], "last": [], "noMoreReplies": true}, "images": [], "id": 46503923}, {"postBy": {"location": "\u65b0\u5317\u5e02\u00b7\u53f0\u7063", "utc": 1471872283000, "level": 0, "avatar": "http://filestoresg1.beetalkmobile.com:8081/file/-3229051244975051255", "name": "\u90b1\u80d6\u4eae"}, "content": "\u4f60\u9858\u610f\u7b49 \u4f46\u4e5f\u8981\u4f60\u9858\u610f\u7d66 \u624d\u6709\u6a5f\u6703\u7b49\u4eba\u7684\u4eba", "urls": [], "replies": {"first": [{"content": "\u7576\u7136", "reply": "", "id": 30620302, "name": "Ny\ud83d\udc8b"}], "last": [], "noMoreReplies": true}, "images": [], "id": 46503952}, {"postBy": {"location": "Taiwan", "utc": 1471872402000, "level": 0, "avatar": "http://filestoresg1.beetalkmobile.com:8081/file/4507153255719014632", "name": "\u4ef2\u6069"}, "content": "\u5176\u5be6\u6211\u4e5f\u6211\u4e0d\u5dee", "urls": [], "replies": {"first": [{"content": "\u54c8\u54c8", "reply": "", "id": 30620310, "name": "Ny\ud83d\udc8b"}], "last": [], "noMoreReplies": true}, "images": [], "id": 46504105}, {"postBy": {"location": "\u65b0\u5317\u5e02\u00b7\u53f0\u7063", "utc": 1471872606000, "level": 0, "avatar": "http://filestoresg1.beetalkmobile.com:8081/file/-30267348804149504", "name": "Blue"}, "content": "\u8eab\u908a\u6c92\u6709\u55ce\uff1f", "urls": [], "replies": {"first": [{"content": "\u662f\u963f", "reply": "", "id": 30620318, "name": "Ny\ud83d\udc8b"}], "last": [], "noMoreReplies": true}, "images": [], "id": 46504379}, {"postBy": {"location": "\u53f0\u5357\u5e02\u00b7\u53f0\u7063", "utc": 1471873334000, "level": 0, "avatar": "http://filestoresg1.beetalkmobile.com:8081/file/5317399878719620354", "name": "\u7b28\u7b28"}, "content": "\u59b3\u597d\u50cf\u5728\u8aaa\u6211\u4ee5\u524d\u7684\u666f\u8c61\u22ef\u22ef<br /><br />\u86cb\u86cb\u3109\u54c0\u50b7", "urls": [], "replies": {"first": [{"content": "\u4ec0\u9ebc\uff1f\uff01", "reply": "", "id": 30620327, "name": "Ny\ud83d\udc8b"}, {"content": "\u59b3\u8aaa\u7684\u9019\u4e9b\u8ddf\u6211\u4ee5\u524d\u3127\u6a23\u3001\u6700\u5f8c\u9084\u662f\u91cd\u50b7\u3001\u7136\u5f8c\u5c31\u3127\u76f4\u5b64\u7368\u5230\u73fe\u5728", "reply": "Ny\ud83d\udc8b", "id": 30622412, "name": "\u7b28\u7b28"}], "last": [], "noMoreReplies": true}, "images": [], "id": 46505409}, {"postBy": {"location": "\u53f0\u4e2d\u5e02\u00b7\u53f0\u7063", "utc": 1471874525000, "level": 0, "avatar": "http://filestoresg1.beetalkmobile.com:8081/file/-3159912835753483090", "name": "\u718a\u4ed4"}, "content": "\ud83d\ude0d\ud83d\ude0d\ud83d\ude0d\ud83d\ude0d", "urls": [], "replies": {"first": [{"content": "\ud83d\ude15", "reply": "", "id": 30620336, "name": "Ny\ud83d\udc8b"}], "last": [], "noMoreReplies": true}, "images": [], "id": 46507136}, {"postBy": {"location": "\u53f0\u5317\u5e02\u00b7\u53f0\u7063", "utc": 1471875231000, "level": 0, "avatar": "http://filestoresg1.beetalkmobile.com:8081/file/537955856351198033", "name": "\u65bd\u5b50"}, "content": "\u80fd\u6bcf\u5929\u62b1\u8457\u5165\u7761<br />\u662f\u6700\u6700\u5927\u7684\u5e78\u798f", "urls": [], "replies": {"first": [{"content": "\u662f\u7684", "reply": "", "id": 30620345, "name": "Ny\ud83d\udc8b"}], "last": [], "noMoreReplies": true}, "images": [], "id": 46508142}]}
