{"noMoreComments": true, "cursorEnd": 0, "id": "4642197", "comments": [{"postBy": {"location": "\u9ad8\u96c4\u5e02\u00b7\u53f0\u7063", "utc": 1475899963000, "level": 0, "avatar": "http://filestoresg1.beetalkmobile.com:8081/file/8670509020949681743", "name": "\u674e\u5c0f\u91f5"}, "content": "\u4fdd\u6eab\u676f\u4e0d\u932f\u963f\uff0c\u96a8\u6642\u90fd\u662f\u71b1\u7684\ud83d\ude06\ud83d\ude06\ud83d\ude06\ud83d\ude06\ud83d\ude06", "urls": [], "replies": {"first": [], "last": [], "noMoreReplies": true}, "images": [], "id": 49881729}]}
