{"noMoreComments": true, "cursorEnd": 0, "id": "4150464", "comments": [{"postBy": {"location": "\u5f70\u5316\u7e23\u00b7\u53f0\u7063", "utc": 1469124450000, "level": 0, "avatar": "http://filestoresg1.beetalkmobile.com:8081/file/566239708120518154", "name": "wen"}, "content": "\u52a0\u6cb9", "urls": [], "replies": {"first": [{"content": "\u597d\u5594", "reply": "", "id": 28919718, "name": "\u53ea\u60f3\u505a\u4f60\u7684\u516c\u4e3b"}], "last": [], "noMoreReplies": true}, "images": [], "id": 44197616}]}
