{"noMoreComments": true, "cursorEnd": 0, "id": "4232758", "comments": [{"postBy": {"location": "\u53f0\u4e2d\u5e02\u00b7\u53f0\u7063", "utc": 1470255829000, "level": 0, "avatar": "http://filestoresg1.beetalkmobile.com:8081/file/6276844702636633345", "name": "\u5347"}, "content": "\u6b64\u70ba\u5546\u696d\u6587\uff08\u5df2\u9055\u53cd\u7248\u898f\uff09\u770b\u5230\u8acb\u522a\u6389 \u5426\u5247\u8e22\u51fa\u4e14\u9ed1\u540d\u55ae", "urls": [], "replies": {"first": [], "last": [], "noMoreReplies": true}, "images": [], "id": 45159905}]}
