{"noMoreComments": true, "cursorEnd": 0, "id": "4726439", "comments": [{"postBy": {"location": "\u53f0\u5317\u5e02\u00b7\u53f0\u7063", "utc": 1477223163000, "level": 0, "avatar": "http://filestoresg1.beetalkmobile.com:8081/file/-6697418884566984288", "name": "chen"}, "content": "\u597d\u7434\u4e00\u628a \u52a0\u6cb9~", "urls": [], "replies": {"first": [], "last": [], "noMoreReplies": true}, "images": [], "id": 50941127}, {"postBy": {"location": "\u5b9c\u862d\u7e23\u00b7\u53f0\u7063", "utc": 1477283465000, "level": 0, "avatar": "http://filestoresg1.beetalkmobile.com:8081/file/3208232000585518695", "name": "Ch"}, "content": "FENDER AMERICAN SPECIAL TELECASTER?<br /><br />", "urls": [], "replies": {"first": [{"content": "Fender Japan Exclusive Classic 70s Tele Ash Maple Natural", "reply": "", "id": 33773012, "name": "Shen"}], "last": [{"content": "\u4e0d\u53ea\u6307\u677f\u73ab\u7470\u6728\n\u7434\u8eab\u4e5f\u662f\u7528\u73ab\u7470\u6728\nhttp://www.fendercustomshop.com/guitars/telecaster/george-harrison-tribute-rosewood-telecaster-rosewood-fingerboard-natural/", "reply": "Ch", "id": 34117883, "name": "Shen"}, {"content": "\u4e0d\u6127\u662fFender Custom Shop= =", "reply": "", "id": 34127464, "name": "Ch"}], "noMoreReplies": false}, "images": [], "id": 50993528}, {"postBy": {"location": "\u5f70\u5316\u7e23\u00b7\u53f0\u7063", "utc": 1478188855000, "level": 0, "avatar": "http://filestoresg1.beetalkmobile.com:8081/file/6584005388557626150", "name": "\u2719Joe Yang\u2719"}, "content": "\u975e\u5e38\u6f02\u4eae\uff01\u6709\u60f3\u904e\u8f49\u624b\uff1f", "urls": [], "replies": {"first": [], "last": [], "noMoreReplies": true}, "images": [], "id": 51777852}]}
