{"noMoreComments": true, "cursorEnd": 0, "id": "4945861", "comments": [{"postBy": {"location": "\u53f0\u5357\u5e02\u00b7\u53f0\u7063", "utc": 1480354215000, "level": 0, "avatar": "http://filestoresg1.beetalkmobile.com:8081/file/8083584205701565560", "name": "\u93ae\u5b87"}, "content": "\u60e1\u7cbe\u9748\u2299_\u2299", "urls": [], "replies": {"first": [], "last": [], "noMoreReplies": true}, "images": [], "id": 53524266}, {"postBy": {"location": "\u65b0\u7af9\u7e23\u00b7\u53f0\u7063", "utc": 1480356346000, "level": 0, "avatar": "http://filestoresg1.beetalkmobile.com:8081/file/8592670177781179882", "name": "Rickson"}, "content": "\u5c0f\u7cbe\u9748\uff08\u9b54\u602a\uff09", "urls": [], "replies": {"first": [{"content": "\u5c0d\uff5e", "reply": "", "id": 35693955, "name": "\u5154\u5bf6"}], "last": [], "noMoreReplies": true}, "images": [], "id": 53525609}, {"postBy": {"location": "\u53f0\u5317\u5e02\u00b7\u53f0\u7063", "utc": 1480482656000, "level": 0, "avatar": "http://filestoresg1.beetalkmobile.com:8081/file/-8021470570146238068", "name": "\u8d85\u7d1a\u8cfd\u4e9e\u4eba\u4f86\u4e86"}, "content": "\u9019\u662f\uff1f", "urls": [], "replies": {"first": [{"content": "\u5c0f\u7cbe\u9748\u3001\u58de\u7cbe\u9748", "reply": "", "id": 35693984, "name": "\u5154\u5bf6"}, {"content": "\u55ef\u55ef \u77ad\u89e3", "reply": "\u5154\u5bf6", "id": 35694622, "name": "\u8d85\u7d1a\u8cfd\u4e9e\u4eba\u4f86\u4e86"}], "last": [], "noMoreReplies": true}, "images": [], "id": 53612137}, {"postBy": {"location": "\u65b0\u5317\u5e02\u00b7\u53f0\u7063", "utc": 1480506106000, "level": 0, "avatar": "http://filestoresg1.beetalkmobile.com:8081/file/-7916446335220411099", "name": "\u73a9\u5177\u760b\u795e\u699c"}, "content": "\u8718\u86db\u7248\u7684\u6c92\u8cb7\uff1f", "urls": [], "replies": {"first": [{"content": "\u6c92\u6709\u8036\uff0c\u6211\u518d\u52aa\u529b\u641c\u96c6\u4e2d\ud83d\udcaa\ud83c\udffb", "reply": "", "id": 35729961, "name": "\u5154\u5bf6"}, {"content": "\u662f\u9019\u7cfb\u5217\u90fd\u8cb7\u9084\u662f\u53ea\u6536\u6050\u6016\u7684", "reply": "", "id": 35744369, "name": "\u73a9\u5177\u760b\u795e\u699c"}], "last": [], "noMoreReplies": true}, "images": [], "id": 53631889}, {"postBy": {"location": "\u82d7\u6817\u7e23\u00b7\u53f0\u7063", "utc": 1481137970000, "level": 0, "avatar": "http://filestoresg1.beetalkmobile.com:8081/file/4011359270387652294", "name": "\u8056\u93a7"}, "content": "NECA\uff1f<br />", "urls": [], "replies": {"first": [{"content": "\u597d\u591a\u54e6\uff01", "reply": "", "id": 36063265, "name": "\u5154\u5bf6"}], "last": [], "noMoreReplies": true}, "images": ["http://filestoresg1.beetalkmobile.com:8081/file/8b047b4099c9bb03043ea387c61032ce", "http://filestoresg1.beetalkmobile.com:8081/file/b5cb6d32254dfdeeb14368ab287cdcf0", "http://filestoresg1.beetalkmobile.com:8081/file/95ab2aad3fb40f5e7d5ac05692d5971f", "http://filestoresg1.beetalkmobile.com:8081/file/0a4ff9aee8d69fc80ef2db746bdd114d", "http://filestoresg1.beetalkmobile.com:8081/file/fc8b4211d6967db7a85649c1160901e3", "http://filestoresg1.beetalkmobile.com:8081/file/d9ddc825dd32bc9b0406c3835475189f"], "id": 54112293}]}
