{"noMoreComments": true, "cursorEnd": 0, "id": "4989584", "comments": [{"postBy": {"location": "\u65b0\u7af9\u7e23\u00b7\u53f0\u7063", "utc": 1481052757000, "level": 0, "avatar": "http://filestoresg1.beetalkmobile.com:8081/file/-5758461232623888496", "name": "\u52c7\u8005\u9b25\u60e1\u9f8d"}, "content": "\u5e78\u904b", "urls": [], "replies": {"first": [], "last": [], "noMoreReplies": true}, "images": [], "id": 54048768}, {"postBy": {"location": "\u53f0\u4e2d\u5e02\u00b7\u53f0\u7063", "utc": 1481073028000, "level": 0, "avatar": "http://filestoresg1.beetalkmobile.com:8081/file/5891665995459716009", "name": "\u9ebb\u7169\u770b\u81ea\u4ecb\u5728+"}, "content": "\u54c8\u54c8\u54c8\u54c8\u54c8\u54c8\u54c8\u54c8\u54c8\u54c8\u54c8\u54c8\u54c8\u54c8\u54c8<br /><br />\u5543  \u6211\u7b11\u7684\u597d\u5927\u8072\ud83d\ude02\ud83d\ude02\ud83d\ude02", "urls": [], "replies": {"first": [], "last": [], "noMoreReplies": true}, "images": [], "id": 54055974}, {"postBy": {"location": "\u5947\u7eb3", "utc": 1481123977000, "level": 0, "avatar": "http://filestoresg1.beetalkmobile.com:8081/file/6510036828081578425", "name": "\u5e0c\u74e6\u90a3"}, "content": "\u4f60\u653e\u932f\u7248\u4e86\u5566\uff01", "urls": [], "replies": {"first": [], "last": [], "noMoreReplies": true}, "images": [], "id": 54101621}, {"postBy": {"location": "\u5c4f\u6771\u7e23\u00b7\u53f0\u7063", "utc": 1481130469000, "level": 0, "avatar": "http://filestoresg1.beetalkmobile.com:8081/file/6469235048372741388", "name": "\u5927\u4ec1\u54e5"}, "content": "\u9760\u6208", "urls": [], "replies": {"first": [], "last": [], "noMoreReplies": true}, "images": [], "id": 54108258}, {"postBy": {"location": "\u65b0\u5317\u5e02\u00b7\u53f0\u7063", "utc": 1481160733000, "level": 0, "avatar": "http://filestoresg1.beetalkmobile.com:8081/file/3117087995063244321", "name": "\u51b7\u51b7"}, "content": "\u6211\u7b11\u4e86\ud83d\ude01", "urls": [], "replies": {"first": [], "last": [], "noMoreReplies": true}, "images": [], "id": 54120858}, {"postBy": {"location": "Changhua County\u00b7Taiwan", "utc": 1481162270000, "level": 0, "avatar": "http://filestoresg1.beetalkmobile.com:8081/file/6609103925834048555", "name": "\u7fd4"}, "content": "\u65bc\u662f\u63db\u5b83\u5e6b\u4f60\u9a0e~", "urls": [], "replies": {"first": [], "last": [], "noMoreReplies": true}, "images": [], "id": 54121813}]}
