{"noMoreComments": true, "cursorEnd": 0, "id": "4263800", "comments": [{"postBy": {"location": "\u53f0\u4e2d\u5e02\u00b7\u53f0\u7063", "utc": 1470661186000, "level": 0, "avatar": "http://filestoresg1.beetalkmobile.com:8081/file/-2438019690125407427", "name": "Ryan"}, "content": "\u6211\u6bcf\u5929\u90fd\u60f3\u7576\u7761\u87f2\u310d\u311f\u7a7a", "urls": [], "replies": {"first": [], "last": [], "noMoreReplies": true}, "images": [], "id": 45493112}, {"postBy": {"location": "Taipei City\u00b7Taiwan", "utc": 1470662336000, "level": 0, "avatar": "http://filestoresg1.beetalkmobile.com:8081/file/-8465014672138860922", "name": "\u9673\u8077\u8c50"}, "content": "\u70ba\u4ec0\u9ebc\u8981\u653e\u68c4\u5462\uff1f", "urls": [], "replies": {"first": [], "last": [], "noMoreReplies": true}, "images": [], "id": 45494472}, {"postBy": {"location": "\u53f0\u5317\u5e02\u00b7\u53f0\u7063", "utc": 1470662360000, "level": 0, "avatar": "http://filestoresg1.beetalkmobile.com:8081/file/-8465014672138860922", "name": "\u9673\u8077\u8c50"}, "content": "\u52c7\u6562\u885d\u51fa\u53bb\u4e0d\u8981\u754f\u61fc", "urls": [], "replies": {"first": [], "last": [], "noMoreReplies": true}, "images": [], "id": 45494507}, {"postBy": {"location": "\u65b0\u5317\u5e02\u00b7\u53f0\u7063", "utc": 1470668015000, "level": 0, "avatar": "http://filestoresg1.beetalkmobile.com:8081/file/6778860835410741903", "name": "\u63da\u5b85(\u5c0b\u7de3)"}, "content": "\u4eba\u751f\u662f\u7f8e\u597d\u7684<br />\u5225\u653e\u68c4", "urls": [], "replies": {"first": [], "last": [], "noMoreReplies": true}, "images": [], "id": 45502079}, {"postBy": {"location": "\u65b0\u5317\u5e02\u00b7\u53f0\u7063", "utc": 1471502389000, "level": 0, "avatar": "http://filestoresg1.beetalkmobile.com:8081/file/-7598789728944251644", "name": "\ud83d\udc23 \u5c0f\u96de\ud83d\udc23"}, "content": "\u55e8", "urls": [], "replies": {"first": [], "last": [], "noMoreReplies": true}, "images": [], "id": 46193687}, {"postBy": {"location": "\u5f70\u5316\u7e23\u00b7\u53f0\u7063", "utc": 1471503693000, "level": 0, "avatar": "http://filestoresg1.beetalkmobile.com:8081/file/5275189619657086471", "name": "jung"}, "content": "\u653e\u68c4\u4ec0\u9ebc\uff1f", "urls": [], "replies": {"first": [], "last": [], "noMoreReplies": true}, "images": [], "id": 46194877}, {"postBy": {"location": "\u53f0\u5317\u5e02\u00b7\u53f0\u7063", "utc": 1471534996000, "level": 0, "avatar": "http://filestoresg1.beetalkmobile.com:8081/file/-6120867962750330793", "name": "\u5fd7\u6469"}, "content": "\u4e0a\u8ab2\u6253\u547c\u55ce\uff1f", "urls": [], "replies": {"first": [], "last": [], "noMoreReplies": true}, "images": [], "id": 46228870}, {"postBy": {"location": "\u53f0\u5317\u5e02\u00b7\u53f0\u7063", "utc": 1471623235000, "level": 0, "avatar": "http://filestoresg1.beetalkmobile.com:8081/file/-6848025579714806428", "name": "\u59dc"}, "content": "\u52a0\u597d\u53cb", "urls": [], "replies": {"first": [], "last": [], "noMoreReplies": true}, "images": [], "id": 46302948}, {"postBy": {"location": "\u65b0\u5317\u5e02\u00b7\u53f0\u7063", "utc": 1471631382000, "level": 0, "avatar": "http://filestoresg1.beetalkmobile.com:8081/file/8002352299047887196", "name": "Cruz huang"}, "content": "Hi", "urls": [], "replies": {"first": [], "last": [], "noMoreReplies": true}, "images": [], "id": 46310034}, {"postBy": {"location": "\u53f0\u5317\u5e02\u00b7\u53f0\u7063", "utc": 1471662726000, "level": 0, "avatar": "http://filestoresg1.beetalkmobile.com:8081/file/7062413874742843071", "name": "Nickname"}, "content": "\u54c8\u54c8\u52a0\u6cb9\u963f \u52a0\u59b3\u56c9", "urls": [], "replies": {"first": [], "last": [], "noMoreReplies": true}, "images": [], "id": 46326119}, {"postBy": {"location": "\u53f0\u5357\u5e02\u00b7\u53f0\u7063", "utc": 1471767088000, "level": 0, "avatar": "http://filestoresg1.beetalkmobile.com:8081/file/-6816370658424010602", "name": "\u963f\u52f3"}, "content": "\u597d\u53ef\u611b", "urls": [], "replies": {"first": [], "last": [], "noMoreReplies": true}, "images": [], "id": 46414787}, {"postBy": {"location": "\u65b0\u5317\u5e02\u00b7\u53f0\u7063", "utc": 1495020328000, "level": 0, "avatar": "http://filestoresg1.beetalkmobile.com:8081/file/8037461886880944069", "name": "\u5ffd\u7136\u807d\u898b\u4e0b\u96e8\u7684\u8072\u97f3"}, "content": "\u600e\u9ebc\u90a3\u9ebc\u7f8e", "urls": [], "replies": {"first": [], "last": [], "noMoreReplies": true}, "images": [], "id": 65014037}]}
