{"noMoreComments": true, "cursorEnd": 0, "id": "4666323", "comments": [{"postBy": {"location": "\u6843\u5712\u5e02\u00b7\u53f0\u7063", "utc": 1476240936000, "level": 0, "avatar": "http://filestoresg1.beetalkmobile.com:8081/file/-5099559098679344932", "name": "\ud83c\udd94\u990a\u6a02\u591a\u591a-\u591a\u591a\u7238\ud83c\udf7c"}, "content": "\u84b8\u7684", "urls": [], "replies": {"first": [], "last": [], "noMoreReplies": true}, "images": ["http://filestoresg1.beetalkmobile.com:8081/file/d35fb2b93e27c64a3ed78f14c15bffd6"], "id": 50183495}, {"postBy": {"location": "\u65b0\u7af9\u7e23\u00b7\u53f0\u7063", "utc": 1476241425000, "level": 0, "avatar": "http://filestoresg1.beetalkmobile.com:8081/file/-8364064112114686185", "name": "Andy"}, "content": "\u662f\u554a\uff01\u5728\u54ea\u88e1\uff0c\u6bcf\u500b\u4eba\u90fd\u60f3\u77e5\u9053\u3002", "urls": [], "replies": {"first": [], "last": [], "noMoreReplies": true}, "images": [], "id": 50183982}, {"postBy": {"location": "\u6843\u5712\u5e02\u00b7\u53f0\u7063", "utc": 1476251407000, "level": 0, "avatar": "http://filestoresg1.beetalkmobile.com:8081/file/7655324439644747028", "name": "\u5c0f\u6176"}, "content": "\u6211\u4e5f\u60f3\u77e5\u9053", "urls": [], "replies": {"first": [], "last": [], "noMoreReplies": true}, "images": [], "id": 50194575}, {"postBy": {"location": "\u9ad8\u96c4\u5e02\u00b7\u53f0\u7063", "utc": 1476289486000, "level": 0, "avatar": "http://filestoresg1.beetalkmobile.com:8081/file/2512673259650807574", "name": "\uff2a\uff2a"}, "content": "\ud83d\ude02\ud83d\ude02\ud83d\ude02\ud83d\ude02\u51e1\u4eba\u90fd\u662f", "urls": [], "replies": {"first": [], "last": [], "noMoreReplies": true}, "images": [], "id": 50240120}, {"postBy": {"location": "\u53f0\u4e2d\u5e02\u00b7\u53f0\u7063", "utc": 1476291839000, "level": 0, "avatar": "http://filestoresg1.beetalkmobile.com:8081/file/3701192535006079263", "name": "O M G "}, "content": "good for you ", "urls": [], "replies": {"first": [{"content": "\u8b1d\u8b1d", "reply": "", "id": 33393042, "name": "O M G "}], "last": [], "noMoreReplies": true}, "images": ["http://filestoresg1.beetalkmobile.com:8081/file/841fc4e86fda276dec17a6bdd2976d94"], "id": 50242910}, {"postBy": {"location": "", "utc": 1476296203000, "level": 0, "avatar": "http://filestoresg1.beetalkmobile.com:8081/file/-5096738853737607040", "name": "\u5c0f\u85b0Cherry"}, "content": "\u8981\u662f\u6709\u7537\u670b\u53cb\u4e5f\u4e0d\u7528\u9019\u9ebc\u591a\u5973\u6027\u770b\u97d3\u5287\u4e86\ud83d\ude02\ud83d\ude1b", "urls": [{"url": "https://instagram.com/p/BLbYaCfDZxt/", "thumbUrl": "https://scontent.cdninstagram.com/t51.2885-15/e15/14596762_972207036258556_9048711114384211968_n.jpg?ig_cache_key=MTM1ODc4NzA1NTA3MzQ2NzUwMQ%3D%3D.2", "description": "See this Instagram video by @cherry2014q1030 \u2022 13 likes", "title": "Instagram video by \u85b0\u5152\ud83d\udcaf \u2022 Oct 11, 2016 at 3:34pm UTC"}], "replies": {"first": [], "last": [], "noMoreReplies": true}, "images": [], "id": 50246563}, {"postBy": {"location": "\u5f70\u5316\u7e23\u00b7\u53f0\u7063", "utc": 1476353722000, "level": 0, "avatar": "http://filestoresg1.beetalkmobile.com:8081/file/1", "name": "\u9f8d\u5377\u98a8"}, "content": "\u592a\u7f8e\u4e86", "urls": [], "replies": {"first": [], "last": [], "noMoreReplies": true}, "images": [], "id": 50292182}]}
